df/VAD.py
df/__init__.py
df/df.py
df/resampler.py
df/requests/__init__.py
df/requests/request.py
df/requests/query/__init__.py
df/requests/query/events.py
df/requests/query/query.py
df/requests/query/text.py
df/requests/query/voice.py
df/requests/user_entities/__init__.py
df/requests/user_entities/user_entities_request.py
dialogflow-client/VAD.py
dialogflow-client/__init__.py
dialogflow-client/dialogflow-client.py
dialogflow-client/resampler.py
dialogflow-client/requests/__init__.py
dialogflow-client/requests/request.py
dialogflow-client/requests/query/__init__.py
dialogflow-client/requests/query/events.py
dialogflow-client/requests/query/query.py
dialogflow-client/requests/query/text.py
dialogflow-client/requests/query/voice.py
dialogflow-client/requests/user_entities/__init__.py
dialogflow-client/requests/user_entities/user_entities_request.py
dialogflow_client-1.2.3.dist-info/DESCRIPTION.rst
dialogflow_client-1.2.3.dist-info/METADATA
dialogflow_client-1.2.3.dist-info/RECORD
dialogflow_client-1.2.3.dist-info/WHEEL
dialogflow_client-1.2.3.dist-info/metadata.json
dialogflow_client-1.2.3.dist-info/top_level.txt
